ptfa/__init__.py
ptfa/generation.py
ptfa/ptfa.py
ptfa-0.2.11.dist-info/LICENSE.md
ptfa-0.2.11.dist-info/METADATA
ptfa-0.2.11.dist-info/WHEEL
ptfa-0.2.11.dist-info/top_level.txt
ptfa-0.2.11.dist-info/RECORD
