Metadata-Version: 2.1
Name: ptfa
Version: 0.2.11
Summary: Probabilistic Targeted Factor Analysis
Author-email: "Miguel C. Herculano" <miguel.herculano@glasgow.ac.uk>, Santiago Montoya-Blandón <Santiago.Montoya-Blandon@glasgow.ac.uk>
Maintainer-email: Santiago Montoya-Blandón <Santiago.Montoya-Blandon@glasgow.ac.uk>, "Miguel C. Herculano" <miguel.herculano@glasgow.ac.uk>
Project-URL: Homepage, https://github.com/smonto2/PTFA
Project-URL: Bug tracking, https://github.com/smonto2/PTFA/issues
Keywords: Partial Least Squares,high-dimensional data,Expectation-Maximization algorithm,missing data,time-series
Classifier: Programming Language :: Python :: 3
Classifier: License :: OSI Approved :: MIT License
Classifier: Operating System :: OS Independent
Requires-Python: >=3.8
License-File: LICENSE.md
Requires-Dist: numpy
Requires-Dist: scikit-learn
